{
  "bps": [
    {
      "i": 1, 
      "p": "0.735", 
      "j": 118, 
      "ix": 0
    }, 
    {
      "i": 2, 
      "p": "0.999", 
      "j": 117, 
      "ix": 0
    }, 
    {
      "i": 3, 
      "p": "0.999", 
      "j": 116, 
      "ix": 0
    }, 
    {
      "i": 4, 
      "p": "0.998", 
      "j": 115, 
      "ix": 0
    }, 
    {
      "i": 5, 
      "p": "0.999", 
      "j": 114, 
      "ix": 0
    }, 
    {
      "i": 6, 
      "p": "0.998", 
      "j": 113, 
      "ix": 0
    }, 
    {
      "i": 8, 
      "p": "0.975", 
      "j": 110, 
      "ix": 0
    }, 
    {
      "i": 9, 
      "p": "0.972", 
      "j": 109, 
      "ix": 0
    }, 
    {
      "i": 10, 
      "p": "0.936", 
      "j": 108, 
      "ix": 0
    }, 
    {
      "i": 11, 
      "p": "0.434", 
      "j": 31, 
      "ix": 1
    }, 
    {
      "i": 11, 
      "p": "0.900", 
      "j": 107, 
      "ix": 0
    }, 
    {
      "i": 12, 
      "p": "0.444", 
      "j": 30, 
      "ix": 1
    }, 
    {
      "i": 12, 
      "p": "0.882", 
      "j": 106, 
      "ix": 0
    }, 
    {
      "i": 13, 
      "p": "0.774", 
      "j": 105, 
      "ix": 0
    }, 
    {
      "i": 14, 
      "p": "0.878", 
      "j": 28, 
      "ix": 0
    }, 
    {
      "i": 14, 
      "p": "0.395", 
      "j": 104, 
      "ix": 2
    }, 
    {
      "i": 15, 
      "p": "0.932", 
      "j": 27, 
      "ix": 0
    }, 
    {
      "i": 16, 
      "p": "0.151", 
      "j": 23, 
      "ix": 3
    }, 
    {
      "i": 16, 
      "p": "0.935", 
      "j": 26, 
      "ix": 0
    }, 
    {
      "i": 17, 
      "p": "0.144", 
      "j": 22, 
      "ix": 3
    }, 
    {
      "i": 17, 
      "p": "0.931", 
      "j": 25, 
      "ix": 0
    }, 
    {
      "i": 18, 
      "p": "0.880", 
      "j": 24, 
      "ix": 0
    }, 
    {
      "i": 20, 
      "p": "0.102", 
      "j": 29, 
      "ix": 4
    }, 
    {
      "i": 26, 
      "p": "0.279", 
      "j": 73, 
      "ix": 2
    }, 
    {
      "i": 27, 
      "p": "0.282", 
      "j": 72, 
      "ix": 2
    }, 
    {
      "i": 28, 
      "p": "0.281", 
      "j": 71, 
      "ix": 2
    }, 
    {
      "i": 29, 
      "p": "0.164", 
      "j": 66, 
      "ix": 5
    }, 
    {
      "i": 30, 
      "p": "0.164", 
      "j": 65, 
      "ix": 5
    }, 
    {
      "i": 30, 
      "p": "0.176", 
      "j": 68, 
      "ix": 6
    }, 
    {
      "i": 30, 
      "p": "0.659", 
      "j": 69, 
      "ix": 0
    }, 
    {
      "i": 31, 
      "p": "0.161", 
      "j": 64, 
      "ix": 5
    }, 
    {
      "i": 31, 
      "p": "0.222", 
      "j": 67, 
      "ix": 6
    }, 
    {
      "i": 31, 
      "p": "0.719", 
      "j": 68, 
      "ix": 0
    }, 
    {
      "i": 33, 
      "p": "0.167", 
      "j": 63, 
      "ix": 5
    }, 
    {
      "i": 33, 
      "p": "0.974", 
      "j": 66, 
      "ix": 0
    }, 
    {
      "i": 34, 
      "p": "0.168", 
      "j": 62, 
      "ix": 5
    }, 
    {
      "i": 34, 
      "p": "0.976", 
      "j": 65, 
      "ix": 0
    }, 
    {
      "i": 35, 
      "p": "0.154", 
      "j": 61, 
      "ix": 5
    }, 
    {
      "i": 35, 
      "p": "0.975", 
      "j": 64, 
      "ix": 0
    }, 
    {
      "i": 36, 
      "p": "0.140", 
      "j": 60, 
      "ix": 5
    }, 
    {
      "i": 36, 
      "p": "0.958", 
      "j": 63, 
      "ix": 0
    }, 
    {
      "i": 37, 
      "p": "0.127", 
      "j": 59, 
      "ix": 5
    }, 
    {
      "i": 40, 
      "p": "0.944", 
      "j": 61, 
      "ix": 0
    }, 
    {
      "i": 41, 
      "p": "0.986", 
      "j": 60, 
      "ix": 0
    }, 
    {
      "i": 42, 
      "p": "0.987", 
      "j": 59, 
      "ix": 0
    }, 
    {
      "i": 43, 
      "p": "0.989", 
      "j": 58, 
      "ix": 0
    }, 
    {
      "i": 44, 
      "p": "0.967", 
      "j": 57, 
      "ix": 0
    }, 
    {
      "i": 46, 
      "p": "0.976", 
      "j": 55, 
      "ix": 0
    }, 
    {
      "i": 47, 
      "p": "0.992", 
      "j": 54, 
      "ix": 0
    }, 
    {
      "i": 48, 
      "p": "0.966", 
      "j": 53, 
      "ix": 0
    }, 
    {
      "i": 67, 
      "p": "0.127", 
      "j": 79, 
      "ix": 7
    }, 
    {
      "i": 67, 
      "p": "0.348", 
      "j": 108, 
      "ix": 1
    }, 
    {
      "i": 68, 
      "p": "0.134", 
      "j": 78, 
      "ix": 7
    }, 
    {
      "i": 68, 
      "p": "0.384", 
      "j": 107, 
      "ix": 1
    }, 
    {
      "i": 69, 
      "p": "0.134", 
      "j": 77, 
      "ix": 7
    }, 
    {
      "i": 69, 
      "p": "0.342", 
      "j": 97, 
      "ix": 8
    }, 
    {
      "i": 69, 
      "p": "0.384", 
      "j": 106, 
      "ix": 1
    }, 
    {
      "i": 70, 
      "p": "0.130", 
      "j": 76, 
      "ix": 7
    }, 
    {
      "i": 70, 
      "p": "0.390", 
      "j": 96, 
      "ix": 8
    }, 
    {
      "i": 70, 
      "p": "0.370", 
      "j": 105, 
      "ix": 1
    }, 
    {
      "i": 71, 
      "p": "0.401", 
      "j": 95, 
      "ix": 8
    }, 
    {
      "i": 71, 
      "p": "0.284", 
      "j": 104, 
      "ix": 1
    }, 
    {
      "i": 72, 
      "p": "0.401", 
      "j": 94, 
      "ix": 8
    }, 
    {
      "i": 73, 
      "p": "0.105", 
      "j": 82, 
      "ix": 9
    }, 
    {
      "i": 73, 
      "p": "0.386", 
      "j": 93, 
      "ix": 8
    }, 
    {
      "i": 73, 
      "p": "0.590", 
      "j": 104, 
      "ix": 0
    }, 
    {
      "i": 74, 
      "p": "0.104", 
      "j": 81, 
      "ix": 9
    }, 
    {
      "i": 74, 
      "p": "0.859", 
      "j": 103, 
      "ix": 0
    }, 
    {
      "i": 75, 
      "p": "0.102", 
      "j": 80, 
      "ix": 9
    }, 
    {
      "i": 75, 
      "p": "0.409", 
      "j": 91, 
      "ix": 8
    }, 
    {
      "i": 75, 
      "p": "0.881", 
      "j": 102, 
      "ix": 0
    }, 
    {
      "i": 76, 
      "p": "0.411", 
      "j": 90, 
      "ix": 8
    }, 
    {
      "i": 76, 
      "p": "0.885", 
      "j": 101, 
      "ix": 0
    }, 
    {
      "i": 77, 
      "p": "0.412", 
      "j": 89, 
      "ix": 8
    }, 
    {
      "i": 77, 
      "p": "0.888", 
      "j": 100, 
      "ix": 0
    }, 
    {
      "i": 78, 
      "p": "0.412", 
      "j": 88, 
      "ix": 8
    }, 
    {
      "i": 78, 
      "p": "0.888", 
      "j": 99, 
      "ix": 0
    }, 
    {
      "i": 79, 
      "p": "0.886", 
      "j": 98, 
      "ix": 0
    }, 
    {
      "i": 80, 
      "p": "0.110", 
      "j": 87, 
      "ix": 10
    }, 
    {
      "i": 80, 
      "p": "0.860", 
      "j": 97, 
      "ix": 0
    }, 
    {
      "i": 81, 
      "p": "0.105", 
      "j": 86, 
      "ix": 10
    }, 
    {
      "i": 81, 
      "p": "0.265", 
      "j": 89, 
      "ix": 11
    }, 
    {
      "i": 82, 
      "p": "0.267", 
      "j": 88, 
      "ix": 11
    }, 
    {
      "i": 82, 
      "p": "0.443", 
      "j": 94, 
      "ix": 12
    }, 
    {
      "i": 83, 
      "p": "0.217", 
      "j": 87, 
      "ix": 11
    }, 
    {
      "i": 83, 
      "p": "0.408", 
      "j": 93, 
      "ix": 12
    }, 
    {
      "i": 83, 
      "p": "0.119", 
      "j": 96, 
      "ix": 13
    }, 
    {
      "i": 84, 
      "p": "0.213", 
      "j": 93, 
      "ix": 14
    }, 
    {
      "i": 84, 
      "p": "0.114", 
      "j": 95, 
      "ix": 13
    }, 
    {
      "i": 84, 
      "p": "0.151", 
      "j": 97, 
      "ix": 15
    }, 
    {
      "i": 85, 
      "p": "0.240", 
      "j": 96, 
      "ix": 16
    }, 
    {
      "i": 86, 
      "p": "0.325", 
      "j": 93, 
      "ix": 17
    }, 
    {
      "i": 86, 
      "p": "0.243", 
      "j": 95, 
      "ix": 16
    }, 
    {
      "i": 87, 
      "p": "0.326", 
      "j": 92, 
      "ix": 17
    }, 
    {
      "i": 87, 
      "p": "0.238", 
      "j": 94, 
      "ix": 16
    }, 
    {
      "i": 88, 
      "p": "0.133", 
      "j": 93, 
      "ix": 18
    }, 
    {
      "i": 88, 
      "p": "0.144", 
      "j": 107, 
      "ix": 7
    }, 
    {
      "i": 89, 
      "p": "0.146", 
      "j": 106, 
      "ix": 7
    }, 
    {
      "i": 90, 
      "p": "0.149", 
      "j": 105, 
      "ix": 7
    }, 
    {
      "i": 91, 
      "p": "0.151", 
      "j": 104, 
      "ix": 7
    }, 
    {
      "i": 92, 
      "p": "0.152", 
      "j": 103, 
      "ix": 7
    }, 
    {
      "i": 93, 
      "p": "0.153", 
      "j": 102, 
      "ix": 7
    }
  ], 
  "baseProbs": [
    [
      1, 
      "0.540"
    ], 
    [
      2, 
      "0.998"
    ], 
    [
      3, 
      "0.999"
    ], 
    [
      4, 
      "0.997"
    ], 
    [
      5, 
      "0.998"
    ], 
    [
      6, 
      "0.997"
    ], 
    [
      7, 
      "0.003"
    ], 
    [
      8, 
      "0.953"
    ], 
    [
      9, 
      "0.947"
    ], 
    [
      10, 
      "0.881"
    ], 
    [
      11, 
      "0.998"
    ], 
    [
      12, 
      "0.977"
    ], 
    [
      13, 
      "0.610"
    ], 
    [
      14, 
      "0.934"
    ], 
    [
      15, 
      "0.895"
    ], 
    [
      16, 
      "0.916"
    ], 
    [
      17, 
      "0.912"
    ], 
    [
      18, 
      "0.802"
    ], 
    [
      19, 
      "0.022"
    ], 
    [
      20, 
      "0.030"
    ], 
    [
      21, 
      "0.028"
    ], 
    [
      22, 
      "0.051"
    ], 
    [
      23, 
      "0.045"
    ], 
    [
      24, 
      "0.784"
    ], 
    [
      25, 
      "0.871"
    ], 
    [
      26, 
      "0.956"
    ], 
    [
      27, 
      "0.958"
    ], 
    [
      28, 
      "0.879"
    ], 
    [
      29, 
      "0.056"
    ], 
    [
      30, 
      "0.716"
    ], 
    [
      31, 
      "0.797"
    ], 
    [
      32, 
      "0.004"
    ], 
    [
      33, 
      "0.987"
    ], 
    [
      34, 
      "0.999"
    ], 
    [
      35, 
      "0.991"
    ], 
    [
      36, 
      "0.954"
    ], 
    [
      37, 
      "0.017"
    ], 
    [
      38, 
      "0.006"
    ], 
    [
      39, 
      "0.007"
    ], 
    [
      40, 
      "0.907"
    ], 
    [
      41, 
      "0.987"
    ], 
    [
      42, 
      "0.976"
    ], 
    [
      43, 
      "0.989"
    ], 
    [
      44, 
      "0.945"
    ], 
    [
      45, 
      "0.012"
    ], 
    [
      46, 
      "0.955"
    ], 
    [
      47, 
      "0.991"
    ], 
    [
      48, 
      "0.940"
    ], 
    [
      49, 
      "0.006"
    ], 
    [
      50, 
      "0.000"
    ], 
    [
      51, 
      "0.007"
    ], 
    [
      52, 
      "0.007"
    ], 
    [
      53, 
      "0.948"
    ], 
    [
      54, 
      "0.990"
    ], 
    [
      55, 
      "0.963"
    ], 
    [
      56, 
      "0.008"
    ], 
    [
      57, 
      "0.943"
    ], 
    [
      58, 
      "0.988"
    ], 
    [
      59, 
      "0.999"
    ], 
    [
      60, 
      "0.998"
    ], 
    [
      61, 
      "0.915"
    ], 
    [
      62, 
      "0.034"
    ], 
    [
      63, 
      "0.953"
    ], 
    [
      64, 
      "0.985"
    ], 
    [
      65, 
      "0.984"
    ], 
    [
      66, 
      "0.991"
    ], 
    [
      67, 
      "0.213"
    ], 
    [
      68, 
      "0.736"
    ], 
    [
      69, 
      "0.730"
    ], 
    [
      70, 
      "0.321"
    ], 
    [
      71, 
      "0.343"
    ], 
    [
      72, 
      "0.259"
    ], 
    [
      73, 
      "0.593"
    ], 
    [
      74, 
      "0.753"
    ], 
    [
      75, 
      "0.969"
    ], 
    [
      76, 
      "0.975"
    ], 
    [
      77, 
      "0.980"
    ], 
    [
      78, 
      "0.984"
    ], 
    [
      79, 
      "0.811"
    ], 
    [
      80, 
      "0.770"
    ], 
    [
      81, 
      "0.099"
    ], 
    [
      82, 
      "0.285"
    ], 
    [
      83, 
      "0.241"
    ], 
    [
      84, 
      "0.086"
    ], 
    [
      85, 
      "0.070"
    ], 
    [
      86, 
      "0.181"
    ], 
    [
      87, 
      "0.229"
    ], 
    [
      88, 
      "0.284"
    ], 
    [
      89, 
      "0.266"
    ], 
    [
      90, 
      "0.194"
    ], 
    [
      91, 
      "0.197"
    ], 
    [
      92, 
      "0.135"
    ], 
    [
      93, 
      "0.523"
    ], 
    [
      94, 
      "0.424"
    ], 
    [
      95, 
      "0.258"
    ], 
    [
      96, 
      "0.246"
    ], 
    [
      97, 
      "0.889"
    ], 
    [
      98, 
      "0.793"
    ], 
    [
      99, 
      "0.805"
    ], 
    [
      100, 
      "0.804"
    ], 
    [
      101, 
      "0.801"
    ], 
    [
      102, 
      "0.813"
    ], 
    [
      103, 
      "0.777"
    ], 
    [
      104, 
      "0.619"
    ], 
    [
      105, 
      "0.773"
    ], 
    [
      106, 
      "0.961"
    ], 
    [
      107, 
      "0.989"
    ], 
    [
      108, 
      "0.999"
    ], 
    [
      109, 
      "0.950"
    ], 
    [
      110, 
      "0.958"
    ], 
    [
      111, 
      "0.000"
    ], 
    [
      112, 
      "0.000"
    ], 
    [
      113, 
      "0.997"
    ], 
    [
      114, 
      "0.998"
    ], 
    [
      115, 
      "0.997"
    ], 
    [
      116, 
      "0.999"
    ], 
    [
      117, 
      "0.998"
    ], 
    [
      118, 
      "0.539"
    ]
  ], 
  "structs": [
    {
      "ix": 0, 
      "sprob": 0.015815728017813863, 
      "struct": "((((((.(((((((((((.....))))).((.((((...(((((.(((....))).))))).)))).))...((((((((................))))))))))))))..))))))"
    }, 
    {
      "ix": 12, 
      "sprob": 0.008264602833927347, 
      "struct": "((((((.(((((((((((.....))))).((.((((...(((((.(((....))).))))).)))).))...((((((((.((.........))..))))))))))))))..))))))"
    }, 
    {
      "ix": 8, 
      "sprob": 0.007026761091020274, 
      "struct": "((((((.(((((((((((.....)))))....((((...(((((.(((....))).))))).))))..(((((.((((.........)))).))))).......))))))..))))))"
    }, 
    {
      "ix": 17, 
      "sprob": 0.0043187174138064905, 
      "struct": "((((((.(((((((((((.....))))).((.((((...(((((.(((....))).))))).)))).))...((((((((.....((....))...))))))))))))))..))))))"
    }, 
    {
      "ix": 1, 
      "sprob": 0.0043187174138064905, 
      "struct": "((((((.((.((.(((((.....))))).)).((((...(((((.(((....))).))))).))))(((((..(((((((................))))))))))))))..))))))"
    }, 
    {
      "ix": 2, 
      "sprob": 0.003121915815361962, 
      "struct": "((((((.(((((((...........(((.((.((((...(((((.(((....))).))))).)))).)).)))(((((((................))))))))))))))..))))))"
    }, 
    {
      "ix": 11, 
      "sprob": 0.0022567714958726054, 
      "struct": "((((((.(((((((((((.....))))).((.((((...(((((.(((....))).))))).)))).))...(((((((((((...))).......))))))))))))))..))))))"
    }, 
    {
      "ix": 14, 
      "sprob": 0.0022567714958726054, 
      "struct": "((((((.(((((((((((.....))))).((.((((...(((((.(((....))).))))).)))).))...((((((((...(........)...))))))))))))))..))))))"
    }, 
    {
      "ix": 7, 
      "sprob": 0.0013870342583103233, 
      "struct": "((((((.(((((.(((((.....))))).)).((((...(((((.(((....))).))))).))))(((((...)))))........((((((........)))))))))..))))))"
    }, 
    {
      "ix": 3, 
      "sprob": 0.0013870342583103233, 
      "struct": "((((((.(((((((.((....))..(((.((.((((...(((((.(((....))).))))).)))).)).)))(((((((................))))))))))))))..))))))"
    }, 
    {
      "ix": 6, 
      "sprob": 0.0013870342583103233, 
      "struct": "((((((.(((((((((((.....))))).((.((((...(((((.(((....))).))))).))))))(((((.((((.........)))).))))).......))))))..))))))"
    }, 
    {
      "ix": 9, 
      "sprob": 0.0011792893807548723, 
      "struct": "((((((.(((((.(((((.....))))).)).((((...(((((.(((....))).))))).)))).....((((....))))....((((((........)))))))))..))))))"
    }, 
    {
      "ix": 16, 
      "sprob": 0.0011792893807548723, 
      "struct": "((((((.(((((((((((.....))))).((.((((...(((((.(((....))).))))).)))).))...((((((((....(((......)))))))))))))))))..))))))"
    }, 
    {
      "ix": 15, 
      "sprob": 0.0006162446867592466, 
      "struct": "((((((.(((((((((((.....))))).((.((((...(((((.(((....))).))))).)))).))...(((((((....((((......)))))))))))))))))..))))))"
    }, 
    {
      "ix": 18, 
      "sprob": 0.0005239458295190853, 
      "struct": "((((((.(((((((((((.....))))).((.((((...(((((.(((....))).))))).)))).))...((((((((....((((....))))))))))))))))))..))))))"
    }, 
    {
      "ix": 10, 
      "sprob": 0.0004454711548331658, 
      "struct": "((((((.(((((((((((.....)))))....((((...(((((.(((....))).))))).))))..(((((.((((.((....)))))).))))).......))))))..))))))"
    }, 
    {
      "ix": 13, 
      "sprob": 0.00037875012760487054, 
      "struct": "((((((.(((((((((((.....))))).((.((((...(((((.(((....))).))))).)))).))...((((((((..((.((....)).))))))))))))))))..))))))"
    }, 
    {
      "ix": 4, 
      "sprob": 0.0002737910125029067, 
      "struct": "((((((.(((((((....(((......)))..((((...(((((.(((....))).))))).))))..(((((.((((.........)))).)))))......)))))))..))))))"
    }, 
    {
      "ix": 5, 
      "sprob": 0.00023278360405036525, 
      "struct": "((((((.(((((((((((.....)))))(((.(((((..((.((........))))..))))))))..(((((.((((.........)))).))))).......))))))..))))))"
    }
  ], 
  "seq": "UGAAACGGAGGAGACGUUACAGCAACGUGUCAGCUGAAAUGAUGGGCGUAGACGCACGUCAGCGGCGGAAAUGGUUUCUAUCAAAAUGAAAGUGUUUAGAGAUUUUCCUCAAGUUUCA"
}
