{
  "bps": [
    {
      "i": 1, 
      "p": "0.735", 
      "j": 118, 
      "ix": 0
    }, 
    {
      "i": 2, 
      "p": "0.999", 
      "j": 117, 
      "ix": 0
    }, 
    {
      "i": 3, 
      "p": "0.999", 
      "j": 116, 
      "ix": 0
    }, 
    {
      "i": 4, 
      "p": "0.998", 
      "j": 115, 
      "ix": 0
    }, 
    {
      "i": 5, 
      "p": "0.999", 
      "j": 114, 
      "ix": 0
    }, 
    {
      "i": 6, 
      "p": "0.998", 
      "j": 113, 
      "ix": 0
    }, 
    {
      "i": 7, 
      "p": "0.041", 
      "j": 110, 
      "ix": 1
    }, 
    {
      "i": 8, 
      "p": "0.034", 
      "j": 109, 
      "ix": 1
    }, 
    {
      "i": 8, 
      "p": "0.975", 
      "j": 110, 
      "ix": 0
    }, 
    {
      "i": 9, 
      "p": "0.972", 
      "j": 109, 
      "ix": 0
    }, 
    {
      "i": 10, 
      "p": "0.936", 
      "j": 108, 
      "ix": 0
    }, 
    {
      "i": 10, 
      "p": "0.062", 
      "j": 110, 
      "ix": 2
    }, 
    {
      "i": 11, 
      "p": "0.434", 
      "j": 31, 
      "ix": 3
    }, 
    {
      "i": 11, 
      "p": "0.900", 
      "j": 107, 
      "ix": 0
    }, 
    {
      "i": 12, 
      "p": "0.444", 
      "j": 30, 
      "ix": 3
    }, 
    {
      "i": 12, 
      "p": "0.036", 
      "j": 105, 
      "ix": 4
    }, 
    {
      "i": 12, 
      "p": "0.882", 
      "j": 106, 
      "ix": 0
    }, 
    {
      "i": 13, 
      "p": "0.086", 
      "j": 31, 
      "ix": 5
    }, 
    {
      "i": 13, 
      "p": "0.043", 
      "j": 104, 
      "ix": 4
    }, 
    {
      "i": 13, 
      "p": "0.774", 
      "j": 105, 
      "ix": 0
    }, 
    {
      "i": 14, 
      "p": "0.878", 
      "j": 28, 
      "ix": 0
    }, 
    {
      "i": 14, 
      "p": "0.082", 
      "j": 30, 
      "ix": 5
    }, 
    {
      "i": 14, 
      "p": "0.034", 
      "j": 103, 
      "ix": 6
    }, 
    {
      "i": 14, 
      "p": "0.395", 
      "j": 104, 
      "ix": 7
    }, 
    {
      "i": 15, 
      "p": "0.092", 
      "j": 22, 
      "ix": 8
    }, 
    {
      "i": 15, 
      "p": "0.932", 
      "j": 27, 
      "ix": 0
    }, 
    {
      "i": 15, 
      "p": "0.075", 
      "j": 29, 
      "ix": 5
    }, 
    {
      "i": 15, 
      "p": "0.073", 
      "j": 41, 
      "ix": 9
    }, 
    {
      "i": 15, 
      "p": "0.038", 
      "j": 44, 
      "ix": 10
    }, 
    {
      "i": 15, 
      "p": "0.064", 
      "j": 101, 
      "ix": 11
    }, 
    {
      "i": 16, 
      "p": "0.151", 
      "j": 23, 
      "ix": 12
    }, 
    {
      "i": 16, 
      "p": "0.935", 
      "j": 26, 
      "ix": 0
    }, 
    {
      "i": 16, 
      "p": "0.045", 
      "j": 28, 
      "ix": 5
    }, 
    {
      "i": 16, 
      "p": "0.039", 
      "j": 31, 
      "ix": 13
    }, 
    {
      "i": 16, 
      "p": "0.076", 
      "j": 40, 
      "ix": 9
    }, 
    {
      "i": 16, 
      "p": "0.038", 
      "j": 43, 
      "ix": 10
    }, 
    {
      "i": 16, 
      "p": "0.078", 
      "j": 103, 
      "ix": 14
    }, 
    {
      "i": 17, 
      "p": "0.144", 
      "j": 22, 
      "ix": 12
    }, 
    {
      "i": 17, 
      "p": "0.931", 
      "j": 25, 
      "ix": 0
    }, 
    {
      "i": 17, 
      "p": "0.077", 
      "j": 39, 
      "ix": 9
    }, 
    {
      "i": 17, 
      "p": "0.038", 
      "j": 42, 
      "ix": 10
    }, 
    {
      "i": 17, 
      "p": "0.064", 
      "j": 99, 
      "ix": 11
    }, 
    {
      "i": 17, 
      "p": "0.051", 
      "j": 100, 
      "ix": 15
    }, 
    {
      "i": 17, 
      "p": "0.079", 
      "j": 102, 
      "ix": 14
    }, 
    {
      "i": 18, 
      "p": "0.880", 
      "j": 24, 
      "ix": 0
    }, 
    {
      "i": 18, 
      "p": "0.032", 
      "j": 25, 
      "ix": 16
    }, 
    {
      "i": 18, 
      "p": "0.072", 
      "j": 29, 
      "ix": 17
    }, 
    {
      "i": 18, 
      "p": "0.074", 
      "j": 38, 
      "ix": 9
    }, 
    {
      "i": 18, 
      "p": "0.038", 
      "j": 41, 
      "ix": 10
    }, 
    {
      "i": 18, 
      "p": "0.065", 
      "j": 98, 
      "ix": 11
    }, 
    {
      "i": 18, 
      "p": "0.051", 
      "j": 99, 
      "ix": 15
    }, 
    {
      "i": 18, 
      "p": "0.075", 
      "j": 101, 
      "ix": 14
    }, 
    {
      "i": 19, 
      "p": "0.089", 
      "j": 28, 
      "ix": 17
    }, 
    {
      "i": 19, 
      "p": "0.088", 
      "j": 30, 
      "ix": 18
    }, 
    {
      "i": 19, 
      "p": "0.037", 
      "j": 40, 
      "ix": 10
    }, 
    {
      "i": 19, 
      "p": "0.063", 
      "j": 97, 
      "ix": 11
    }, 
    {
      "i": 20, 
      "p": "0.092", 
      "j": 27, 
      "ix": 17
    }, 
    {
      "i": 20, 
      "p": "0.102", 
      "j": 29, 
      "ix": 18
    }, 
    {
      "i": 20, 
      "p": "0.097", 
      "j": 36, 
      "ix": 9
    }, 
    {
      "i": 20, 
      "p": "0.034", 
      "j": 99, 
      "ix": 19
    }, 
    {
      "i": 21, 
      "p": "0.099", 
      "j": 28, 
      "ix": 18
    }, 
    {
      "i": 21, 
      "p": "0.097", 
      "j": 35, 
      "ix": 9
    }, 
    {
      "i": 21, 
      "p": "0.083", 
      "j": 96, 
      "ix": 11
    }, 
    {
      "i": 22, 
      "p": "0.044", 
      "j": 30, 
      "ix": 20
    }, 
    {
      "i": 22, 
      "p": "0.097", 
      "j": 34, 
      "ix": 9
    }, 
    {
      "i": 22, 
      "p": "0.090", 
      "j": 95, 
      "ix": 11
    }, 
    {
      "i": 23, 
      "p": "0.049", 
      "j": 29, 
      "ix": 20
    }, 
    {
      "i": 23, 
      "p": "0.097", 
      "j": 33, 
      "ix": 9
    }, 
    {
      "i": 23, 
      "p": "0.090", 
      "j": 94, 
      "ix": 11
    }, 
    {
      "i": 24, 
      "p": "0.040", 
      "j": 28, 
      "ix": 20
    }, 
    {
      "i": 24, 
      "p": "0.079", 
      "j": 93, 
      "ix": 11
    }, 
    {
      "i": 25, 
      "p": "0.036", 
      "j": 75, 
      "ix": 21
    }, 
    {
      "i": 26, 
      "p": "0.279", 
      "j": 73, 
      "ix": 7
    }, 
    {
      "i": 26, 
      "p": "0.036", 
      "j": 74, 
      "ix": 21
    }, 
    {
      "i": 26, 
      "p": "0.035", 
      "j": 92, 
      "ix": 22
    }, 
    {
      "i": 27, 
      "p": "0.282", 
      "j": 72, 
      "ix": 7
    }, 
    {
      "i": 28, 
      "p": "0.071", 
      "j": 67, 
      "ix": 23
    }, 
    {
      "i": 28, 
      "p": "0.281", 
      "j": 71, 
      "ix": 7
    }, 
    {
      "i": 29, 
      "p": "0.164", 
      "j": 66, 
      "ix": 24
    }, 
    {
      "i": 29, 
      "p": "0.052", 
      "j": 72, 
      "ix": 25
    }, 
    {
      "i": 29, 
      "p": "0.041", 
      "j": 103, 
      "ix": 26
    }, 
    {
      "i": 30, 
      "p": "0.164", 
      "j": 65, 
      "ix": 24
    }, 
    {
      "i": 30, 
      "p": "0.176", 
      "j": 68, 
      "ix": 27
    }, 
    {
      "i": 30, 
      "p": "0.659", 
      "j": 69, 
      "ix": 0
    }, 
    {
      "i": 30, 
      "p": "0.035", 
      "j": 70, 
      "ix": 28
    }, 
    {
      "i": 30, 
      "p": "0.044", 
      "j": 71, 
      "ix": 25
    }, 
    {
      "i": 30, 
      "p": "0.039", 
      "j": 89, 
      "ix": 29
    }, 
    {
      "i": 30, 
      "p": "0.043", 
      "j": 102, 
      "ix": 26
    }, 
    {
      "i": 31, 
      "p": "0.161", 
      "j": 64, 
      "ix": 24
    }, 
    {
      "i": 31, 
      "p": "0.222", 
      "j": 67, 
      "ix": 27
    }, 
    {
      "i": 31, 
      "p": "0.719", 
      "j": 68, 
      "ix": 0
    }, 
    {
      "i": 31, 
      "p": "0.041", 
      "j": 73, 
      "ix": 30
    }, 
    {
      "i": 31, 
      "p": "0.040", 
      "j": 88, 
      "ix": 29
    }, 
    {
      "i": 31, 
      "p": "0.044", 
      "j": 101, 
      "ix": 26
    }, 
    {
      "i": 32, 
      "p": "0.041", 
      "j": 72, 
      "ix": 30
    }, 
    {
      "i": 32, 
      "p": "0.036", 
      "j": 87, 
      "ix": 29
    }, 
    {
      "i": 33, 
      "p": "0.167", 
      "j": 63, 
      "ix": 24
    }, 
    {
      "i": 33, 
      "p": "0.974", 
      "j": 66, 
      "ix": 0
    }, 
    {
      "i": 34, 
      "p": "0.168", 
      "j": 62, 
      "ix": 24
    }, 
    {
      "i": 34, 
      "p": "0.976", 
      "j": 65, 
      "ix": 0
    }, 
    {
      "i": 34, 
      "p": "0.079", 
      "j": 68, 
      "ix": 31
    }, 
    {
      "i": 35, 
      "p": "0.154", 
      "j": 61, 
      "ix": 24
    }, 
    {
      "i": 35, 
      "p": "0.975", 
      "j": 64, 
      "ix": 0
    }, 
    {
      "i": 35, 
      "p": "0.079", 
      "j": 67, 
      "ix": 31
    }, 
    {
      "i": 36, 
      "p": "0.140", 
      "j": 60, 
      "ix": 24
    }, 
    {
      "i": 36, 
      "p": "0.958", 
      "j": 63, 
      "ix": 0
    }, 
    {
      "i": 36, 
      "p": "0.080", 
      "j": 66, 
      "ix": 31
    }, 
    {
      "i": 37, 
      "p": "0.127", 
      "j": 59, 
      "ix": 24
    }, 
    {
      "i": 40, 
      "p": "0.075", 
      "j": 56, 
      "ix": 24
    }, 
    {
      "i": 40, 
      "p": "0.042", 
      "j": 58, 
      "ix": 32
    }, 
    {
      "i": 40, 
      "p": "0.944", 
      "j": 61, 
      "ix": 0
    }, 
    {
      "i": 41, 
      "p": "0.075", 
      "j": 55, 
      "ix": 24
    }, 
    {
      "i": 41, 
      "p": "0.046", 
      "j": 57, 
      "ix": 32
    }, 
    {
      "i": 41, 
      "p": "0.986", 
      "j": 60, 
      "ix": 0
    }, 
    {
      "i": 42, 
      "p": "0.987", 
      "j": 59, 
      "ix": 0
    }, 
    {
      "i": 43, 
      "p": "0.074", 
      "j": 54, 
      "ix": 24
    }, 
    {
      "i": 43, 
      "p": "0.046", 
      "j": 56, 
      "ix": 32
    }, 
    {
      "i": 43, 
      "p": "0.989", 
      "j": 58, 
      "ix": 0
    }, 
    {
      "i": 43, 
      "p": "0.038", 
      "j": 68, 
      "ix": 33
    }, 
    {
      "i": 44, 
      "p": "0.075", 
      "j": 53, 
      "ix": 24
    }, 
    {
      "i": 44, 
      "p": "0.046", 
      "j": 55, 
      "ix": 32
    }, 
    {
      "i": 44, 
      "p": "0.967", 
      "j": 57, 
      "ix": 0
    }, 
    {
      "i": 45, 
      "p": "0.046", 
      "j": 55, 
      "ix": 34
    }, 
    {
      "i": 45, 
      "p": "0.050", 
      "j": 57, 
      "ix": 35
    }, 
    {
      "i": 45, 
      "p": "0.075", 
      "j": 66, 
      "ix": 9
    }, 
    {
      "i": 46, 
      "p": "0.045", 
      "j": 53, 
      "ix": 32
    }, 
    {
      "i": 46, 
      "p": "0.976", 
      "j": 55, 
      "ix": 0
    }, 
    {
      "i": 47, 
      "p": "0.992", 
      "j": 54, 
      "ix": 0
    }, 
    {
      "i": 47, 
      "p": "0.077", 
      "j": 64, 
      "ix": 9
    }, 
    {
      "i": 48, 
      "p": "0.966", 
      "j": 53, 
      "ix": 0
    }, 
    {
      "i": 48, 
      "p": "0.077", 
      "j": 63, 
      "ix": 9
    }, 
    {
      "i": 49, 
      "p": "0.073", 
      "j": 62, 
      "ix": 9
    }, 
    {
      "i": 51, 
      "p": "0.076", 
      "j": 60, 
      "ix": 9
    }, 
    {
      "i": 52, 
      "p": "0.077", 
      "j": 59, 
      "ix": 9
    }, 
    {
      "i": 53, 
      "p": "0.077", 
      "j": 58, 
      "ix": 9
    }, 
    {
      "i": 57, 
      "p": "0.038", 
      "j": 67, 
      "ix": 36
    }, 
    {
      "i": 58, 
      "p": "0.038", 
      "j": 66, 
      "ix": 36
    }, 
    {
      "i": 59, 
      "p": "0.038", 
      "j": 65, 
      "ix": 36
    }, 
    {
      "i": 60, 
      "p": "0.037", 
      "j": 64, 
      "ix": 36
    }, 
    {
      "i": 67, 
      "p": "0.056", 
      "j": 78, 
      "ix": 37
    }, 
    {
      "i": 67, 
      "p": "0.127", 
      "j": 79, 
      "ix": 38
    }, 
    {
      "i": 67, 
      "p": "0.093", 
      "j": 107, 
      "ix": 39
    }, 
    {
      "i": 67, 
      "p": "0.348", 
      "j": 108, 
      "ix": 3
    }, 
    {
      "i": 68, 
      "p": "0.056", 
      "j": 77, 
      "ix": 37
    }, 
    {
      "i": 68, 
      "p": "0.134", 
      "j": 78, 
      "ix": 38
    }, 
    {
      "i": 68, 
      "p": "0.035", 
      "j": 97, 
      "ix": 40
    }, 
    {
      "i": 68, 
      "p": "0.095", 
      "j": 106, 
      "ix": 39
    }, 
    {
      "i": 68, 
      "p": "0.384", 
      "j": 107, 
      "ix": 3
    }, 
    {
      "i": 69, 
      "p": "0.055", 
      "j": 76, 
      "ix": 37
    }, 
    {
      "i": 69, 
      "p": "0.134", 
      "j": 77, 
      "ix": 38
    }, 
    {
      "i": 69, 
      "p": "0.342", 
      "j": 97, 
      "ix": 41
    }, 
    {
      "i": 69, 
      "p": "0.096", 
      "j": 105, 
      "ix": 39
    }, 
    {
      "i": 69, 
      "p": "0.384", 
      "j": 106, 
      "ix": 3
    }, 
    {
      "i": 70, 
      "p": "0.046", 
      "j": 75, 
      "ix": 37
    }, 
    {
      "i": 70, 
      "p": "0.130", 
      "j": 76, 
      "ix": 38
    }, 
    {
      "i": 70, 
      "p": "0.390", 
      "j": 96, 
      "ix": 41
    }, 
    {
      "i": 70, 
      "p": "0.087", 
      "j": 104, 
      "ix": 39
    }, 
    {
      "i": 70, 
      "p": "0.370", 
      "j": 105, 
      "ix": 3
    }, 
    {
      "i": 70, 
      "p": "0.037", 
      "j": 106, 
      "ix": 42
    }, 
    {
      "i": 71, 
      "p": "0.099", 
      "j": 75, 
      "ix": 38
    }, 
    {
      "i": 71, 
      "p": "0.401", 
      "j": 95, 
      "ix": 41
    }, 
    {
      "i": 71, 
      "p": "0.059", 
      "j": 103, 
      "ix": 43
    }, 
    {
      "i": 71, 
      "p": "0.284", 
      "j": 104, 
      "ix": 3
    }, 
    {
      "i": 71, 
      "p": "0.051", 
      "j": 105, 
      "ix": 44
    }, 
    {
      "i": 71, 
      "p": "0.045", 
      "j": 106, 
      "ix": 45
    }, 
    {
      "i": 72, 
      "p": "0.095", 
      "j": 83, 
      "ix": 46
    }, 
    {
      "i": 72, 
      "p": "0.401", 
      "j": 94, 
      "ix": 41
    }, 
    {
      "i": 72, 
      "p": "0.040", 
      "j": 102, 
      "ix": 47
    }, 
    {
      "i": 73, 
      "p": "0.032", 
      "j": 79, 
      "ix": 48
    }, 
    {
      "i": 73, 
      "p": "0.105", 
      "j": 82, 
      "ix": 46
    }, 
    {
      "i": 73, 
      "p": "0.386", 
      "j": 93, 
      "ix": 41
    }, 
    {
      "i": 73, 
      "p": "0.032", 
      "j": 103, 
      "ix": 49
    }, 
    {
      "i": 73, 
      "p": "0.590", 
      "j": 104, 
      "ix": 0
    }, 
    {
      "i": 74, 
      "p": "0.104", 
      "j": 81, 
      "ix": 46
    }, 
    {
      "i": 74, 
      "p": "0.859", 
      "j": 103, 
      "ix": 0
    }, 
    {
      "i": 75, 
      "p": "0.102", 
      "j": 80, 
      "ix": 46
    }, 
    {
      "i": 75, 
      "p": "0.409", 
      "j": 91, 
      "ix": 41
    }, 
    {
      "i": 75, 
      "p": "0.881", 
      "j": 102, 
      "ix": 0
    }, 
    {
      "i": 76, 
      "p": "0.411", 
      "j": 90, 
      "ix": 41
    }, 
    {
      "i": 76, 
      "p": "0.885", 
      "j": 101, 
      "ix": 0
    }, 
    {
      "i": 77, 
      "p": "0.412", 
      "j": 89, 
      "ix": 41
    }, 
    {
      "i": 77, 
      "p": "0.888", 
      "j": 100, 
      "ix": 0
    }, 
    {
      "i": 78, 
      "p": "0.412", 
      "j": 88, 
      "ix": 41
    }, 
    {
      "i": 78, 
      "p": "0.047", 
      "j": 92, 
      "ix": 50
    }, 
    {
      "i": 78, 
      "p": "0.888", 
      "j": 99, 
      "ix": 0
    }, 
    {
      "i": 79, 
      "p": "0.061", 
      "j": 86, 
      "ix": 51
    }, 
    {
      "i": 79, 
      "p": "0.047", 
      "j": 91, 
      "ix": 50
    }, 
    {
      "i": 79, 
      "p": "0.886", 
      "j": 98, 
      "ix": 0
    }, 
    {
      "i": 80, 
      "p": "0.110", 
      "j": 87, 
      "ix": 52
    }, 
    {
      "i": 80, 
      "p": "0.072", 
      "j": 96, 
      "ix": 53
    }, 
    {
      "i": 80, 
      "p": "0.860", 
      "j": 97, 
      "ix": 0
    }, 
    {
      "i": 81, 
      "p": "0.105", 
      "j": 86, 
      "ix": 52
    }, 
    {
      "i": 81, 
      "p": "0.265", 
      "j": 89, 
      "ix": 54
    }, 
    {
      "i": 81, 
      "p": "0.055", 
      "j": 100, 
      "ix": 55
    }, 
    {
      "i": 81, 
      "p": "0.033", 
      "j": 102, 
      "ix": 56
    }, 
    {
      "i": 82, 
      "p": "0.267", 
      "j": 88, 
      "ix": 54
    }, 
    {
      "i": 82, 
      "p": "0.036", 
      "j": 92, 
      "ix": 57
    }, 
    {
      "i": 82, 
      "p": "0.443", 
      "j": 94, 
      "ix": 58
    }, 
    {
      "i": 82, 
      "p": "0.060", 
      "j": 99, 
      "ix": 55
    }, 
    {
      "i": 82, 
      "p": "0.034", 
      "j": 101, 
      "ix": 56
    }, 
    {
      "i": 83, 
      "p": "0.217", 
      "j": 87, 
      "ix": 54
    }, 
    {
      "i": 83, 
      "p": "0.408", 
      "j": 93, 
      "ix": 58
    }, 
    {
      "i": 83, 
      "p": "0.059", 
      "j": 95, 
      "ix": 59
    }, 
    {
      "i": 83, 
      "p": "0.119", 
      "j": 96, 
      "ix": 60
    }, 
    {
      "i": 83, 
      "p": "0.039", 
      "j": 97, 
      "ix": 61
    }, 
    {
      "i": 84, 
      "p": "0.213", 
      "j": 93, 
      "ix": 62
    }, 
    {
      "i": 84, 
      "p": "0.114", 
      "j": 95, 
      "ix": 60
    }, 
    {
      "i": 84, 
      "p": "0.062", 
      "j": 96, 
      "ix": 63
    }, 
    {
      "i": 84, 
      "p": "0.151", 
      "j": 97, 
      "ix": 64
    }, 
    {
      "i": 85, 
      "p": "0.085", 
      "j": 93, 
      "ix": 65
    }, 
    {
      "i": 85, 
      "p": "0.054", 
      "j": 95, 
      "ix": 63
    }, 
    {
      "i": 85, 
      "p": "0.240", 
      "j": 96, 
      "ix": 66
    }, 
    {
      "i": 86, 
      "p": "0.325", 
      "j": 93, 
      "ix": 67
    }, 
    {
      "i": 86, 
      "p": "0.243", 
      "j": 95, 
      "ix": 66
    }, 
    {
      "i": 87, 
      "p": "0.057", 
      "j": 91, 
      "ix": 68
    }, 
    {
      "i": 87, 
      "p": "0.326", 
      "j": 92, 
      "ix": 67
    }, 
    {
      "i": 87, 
      "p": "0.238", 
      "j": 94, 
      "ix": 66
    }, 
    {
      "i": 87, 
      "p": "0.036", 
      "j": 98, 
      "ix": 69
    }, 
    {
      "i": 88, 
      "p": "0.133", 
      "j": 93, 
      "ix": 70
    }, 
    {
      "i": 88, 
      "p": "0.043", 
      "j": 97, 
      "ix": 69
    }, 
    {
      "i": 88, 
      "p": "0.144", 
      "j": 107, 
      "ix": 38
    }, 
    {
      "i": 89, 
      "p": "0.047", 
      "j": 96, 
      "ix": 69
    }, 
    {
      "i": 89, 
      "p": "0.146", 
      "j": 106, 
      "ix": 38
    }, 
    {
      "i": 90, 
      "p": "0.040", 
      "j": 95, 
      "ix": 69
    }, 
    {
      "i": 90, 
      "p": "0.149", 
      "j": 105, 
      "ix": 38
    }, 
    {
      "i": 91, 
      "p": "0.151", 
      "j": 104, 
      "ix": 38
    }, 
    {
      "i": 92, 
      "p": "0.152", 
      "j": 103, 
      "ix": 38
    }, 
    {
      "i": 93, 
      "p": "0.153", 
      "j": 102, 
      "ix": 38
    }, 
    {
      "i": 95, 
      "p": "0.075", 
      "j": 100, 
      "ix": 71
    }, 
    {
      "i": 99, 
      "p": "0.035", 
      "j": 107, 
      "ix": 72
    }, 
    {
      "i": 99, 
      "p": "0.036", 
      "j": 110, 
      "ix": 73
    }, 
    {
      "i": 100, 
      "p": "0.035", 
      "j": 106, 
      "ix": 72
    }, 
    {
      "i": 100, 
      "p": "0.036", 
      "j": 109, 
      "ix": 73
    }, 
    {
      "i": 101, 
      "p": "0.036", 
      "j": 108, 
      "ix": 73
    }
  ], 
  "baseProbs": [
    [
      1, 
      "0.540"
    ], 
    [
      2, 
      "0.998"
    ], 
    [
      3, 
      "0.999"
    ], 
    [
      4, 
      "0.997"
    ], 
    [
      5, 
      "0.998"
    ], 
    [
      6, 
      "0.997"
    ], 
    [
      7, 
      "0.003"
    ], 
    [
      8, 
      "0.953"
    ], 
    [
      9, 
      "0.947"
    ], 
    [
      10, 
      "0.881"
    ], 
    [
      11, 
      "0.998"
    ], 
    [
      12, 
      "0.977"
    ], 
    [
      13, 
      "0.610"
    ], 
    [
      14, 
      "0.934"
    ], 
    [
      15, 
      "0.895"
    ], 
    [
      16, 
      "0.916"
    ], 
    [
      17, 
      "0.912"
    ], 
    [
      18, 
      "0.802"
    ], 
    [
      19, 
      "0.022"
    ], 
    [
      20, 
      "0.030"
    ], 
    [
      21, 
      "0.028"
    ], 
    [
      22, 
      "0.051"
    ], 
    [
      23, 
      "0.045"
    ], 
    [
      24, 
      "0.784"
    ], 
    [
      25, 
      "0.871"
    ], 
    [
      26, 
      "0.956"
    ], 
    [
      27, 
      "0.958"
    ], 
    [
      28, 
      "0.879"
    ], 
    [
      29, 
      "0.056"
    ], 
    [
      30, 
      "0.716"
    ], 
    [
      31, 
      "0.797"
    ], 
    [
      32, 
      "0.004"
    ], 
    [
      33, 
      "0.987"
    ], 
    [
      34, 
      "0.999"
    ], 
    [
      35, 
      "0.991"
    ], 
    [
      36, 
      "0.954"
    ], 
    [
      37, 
      "0.017"
    ], 
    [
      38, 
      "0.006"
    ], 
    [
      39, 
      "0.007"
    ], 
    [
      40, 
      "0.907"
    ], 
    [
      41, 
      "0.987"
    ], 
    [
      42, 
      "0.976"
    ], 
    [
      43, 
      "0.989"
    ], 
    [
      44, 
      "0.945"
    ], 
    [
      45, 
      "0.012"
    ], 
    [
      46, 
      "0.955"
    ], 
    [
      47, 
      "0.991"
    ], 
    [
      48, 
      "0.940"
    ], 
    [
      49, 
      "0.006"
    ], 
    [
      50, 
      "0.000"
    ], 
    [
      51, 
      "0.007"
    ], 
    [
      52, 
      "0.007"
    ], 
    [
      53, 
      "0.948"
    ], 
    [
      54, 
      "0.990"
    ], 
    [
      55, 
      "0.963"
    ], 
    [
      56, 
      "0.008"
    ], 
    [
      57, 
      "0.943"
    ], 
    [
      58, 
      "0.988"
    ], 
    [
      59, 
      "0.999"
    ], 
    [
      60, 
      "0.998"
    ], 
    [
      61, 
      "0.915"
    ], 
    [
      62, 
      "0.034"
    ], 
    [
      63, 
      "0.953"
    ], 
    [
      64, 
      "0.985"
    ], 
    [
      65, 
      "0.984"
    ], 
    [
      66, 
      "0.991"
    ], 
    [
      67, 
      "0.213"
    ], 
    [
      68, 
      "0.736"
    ], 
    [
      69, 
      "0.730"
    ], 
    [
      70, 
      "0.321"
    ], 
    [
      71, 
      "0.343"
    ], 
    [
      72, 
      "0.259"
    ], 
    [
      73, 
      "0.593"
    ], 
    [
      74, 
      "0.753"
    ], 
    [
      75, 
      "0.969"
    ], 
    [
      76, 
      "0.975"
    ], 
    [
      77, 
      "0.980"
    ], 
    [
      78, 
      "0.984"
    ], 
    [
      79, 
      "0.811"
    ], 
    [
      80, 
      "0.770"
    ], 
    [
      81, 
      "0.099"
    ], 
    [
      82, 
      "0.285"
    ], 
    [
      83, 
      "0.241"
    ], 
    [
      84, 
      "0.086"
    ], 
    [
      85, 
      "0.070"
    ], 
    [
      86, 
      "0.181"
    ], 
    [
      87, 
      "0.229"
    ], 
    [
      88, 
      "0.284"
    ], 
    [
      89, 
      "0.266"
    ], 
    [
      90, 
      "0.194"
    ], 
    [
      91, 
      "0.197"
    ], 
    [
      92, 
      "0.135"
    ], 
    [
      93, 
      "0.523"
    ], 
    [
      94, 
      "0.424"
    ], 
    [
      95, 
      "0.258"
    ], 
    [
      96, 
      "0.246"
    ], 
    [
      97, 
      "0.889"
    ], 
    [
      98, 
      "0.793"
    ], 
    [
      99, 
      "0.805"
    ], 
    [
      100, 
      "0.804"
    ], 
    [
      101, 
      "0.801"
    ], 
    [
      102, 
      "0.813"
    ], 
    [
      103, 
      "0.777"
    ], 
    [
      104, 
      "0.619"
    ], 
    [
      105, 
      "0.773"
    ], 
    [
      106, 
      "0.961"
    ], 
    [
      107, 
      "0.989"
    ], 
    [
      108, 
      "0.999"
    ], 
    [
      109, 
      "0.950"
    ], 
    [
      110, 
      "0.958"
    ], 
    [
      111, 
      "0.000"
    ], 
    [
      112, 
      "0.000"
    ], 
    [
      113, 
      "0.997"
    ], 
    [
      114, 
      "0.998"
    ], 
    [
      115, 
      "0.997"
    ], 
    [
      116, 
      "0.999"
    ], 
    [
      117, 
      "0.998"
    ], 
    [
      118, 
      "0.539"
    ]
  ], 
  "structs": [
    {
      "ix": 0, 
      "sprob": 0.015815728017813863, 
      "struct": "((((((.(((((((((((.....))))).((.((((...(((((.(((....))).))))).)))).))...((((((((................))))))))))))))..))))))"
    }, 
    {
      "ix": 58, 
      "sprob": 0.008264602833927347, 
      "struct": "((((((.(((((((((((.....))))).((.((((...(((((.(((....))).))))).)))).))...((((((((.((.........))..))))))))))))))..))))))"
    }, 
    {
      "ix": 41, 
      "sprob": 0.007026761091020274, 
      "struct": "((((((.(((((((((((.....)))))....((((...(((((.(((....))).))))).))))..(((((.((((.........)))).))))).......))))))..))))))"
    }, 
    {
      "ix": 67, 
      "sprob": 0.0043187174138064905, 
      "struct": "((((((.(((((((((((.....))))).((.((((...(((((.(((....))).))))).)))).))...((((((((.....((....))...))))))))))))))..))))))"
    }, 
    {
      "ix": 3, 
      "sprob": 0.0043187174138064905, 
      "struct": "((((((.((.((.(((((.....))))).)).((((...(((((.(((....))).))))).))))(((((..(((((((................))))))))))))))..))))))"
    }, 
    {
      "ix": 7, 
      "sprob": 0.003121915815361962, 
      "struct": "((((((.(((((((...........(((.((.((((...(((((.(((....))).))))).)))).)).)))(((((((................))))))))))))))..))))))"
    }, 
    {
      "ix": 54, 
      "sprob": 0.0022567714958726054, 
      "struct": "((((((.(((((((((((.....))))).((.((((...(((((.(((....))).))))).)))).))...(((((((((((...))).......))))))))))))))..))))))"
    }, 
    {
      "ix": 62, 
      "sprob": 0.0022567714958726054, 
      "struct": "((((((.(((((((((((.....))))).((.((((...(((((.(((....))).))))).)))).))...((((((((...(........)...))))))))))))))..))))))"
    }, 
    {
      "ix": 38, 
      "sprob": 0.0013870342583103233, 
      "struct": "((((((.(((((.(((((.....))))).)).((((...(((((.(((....))).))))).))))(((((...)))))........((((((........)))))))))..))))))"
    }, 
    {
      "ix": 12, 
      "sprob": 0.0013870342583103233, 
      "struct": "((((((.(((((((.((....))..(((.((.((((...(((((.(((....))).))))).)))).)).)))(((((((................))))))))))))))..))))))"
    }, 
    {
      "ix": 27, 
      "sprob": 0.0013870342583103233, 
      "struct": "((((((.(((((((((((.....))))).((.((((...(((((.(((....))).))))).))))))(((((.((((.........)))).))))).......))))))..))))))"
    }, 
    {
      "ix": 46, 
      "sprob": 0.0011792893807548723, 
      "struct": "((((((.(((((.(((((.....))))).)).((((...(((((.(((....))).))))).)))).....((((....))))....((((((........)))))))))..))))))"
    }, 
    {
      "ix": 66, 
      "sprob": 0.0011792893807548723, 
      "struct": "((((((.(((((((((((.....))))).((.((((...(((((.(((....))).))))).)))).))...((((((((....(((......)))))))))))))))))..))))))"
    }, 
    {
      "ix": 64, 
      "sprob": 0.0006162446867592466, 
      "struct": "((((((.(((((((((((.....))))).((.((((...(((((.(((....))).))))).)))).))...(((((((....((((......)))))))))))))))))..))))))"
    }, 
    {
      "ix": 8, 
      "sprob": 0.0005239458295190853, 
      "struct": "((((((.((((((((......)...(((.((.((((...(((((.(((....))).))))).)))).)).)))(((((((................))))))))))))))..))))))"
    }, 
    {
      "ix": 70, 
      "sprob": 0.0005239458295190853, 
      "struct": "((((((.(((((((((((.....))))).((.((((...(((((.(((....))).))))).)))).))...((((((((....((((....))))))))))))))))))..))))))"
    }, 
    {
      "ix": 39, 
      "sprob": 0.0004454711548331658, 
      "struct": "((((((.(((((.(((((.....))))).)).((((...(((((.(((....))).))))).))))((((...(((((((................))))))))))))))..))))))"
    }, 
    {
      "ix": 52, 
      "sprob": 0.0004454711548331658, 
      "struct": "((((((.(((((((((((.....)))))....((((...(((((.(((....))).))))).))))..(((((.((((.((....)))))).))))).......))))))..))))))"
    }, 
    {
      "ix": 71, 
      "sprob": 0.0004454711548331658, 
      "struct": "((((((.(((((.(((((.....))))).)).((((...(((((.(((....))).))))).))))(((((...)))))........((((((.(....).)))))))))..))))))"
    }, 
    {
      "ix": 60, 
      "sprob": 0.00037875012760487054, 
      "struct": "((((((.(((((((((((.....))))).((.((((...(((((.(((....))).))))).)))).))...((((((((..((.((....)).))))))))))))))))..))))))"
    }, 
    {
      "ix": 37, 
      "sprob": 0.00032202232985080887, 
      "struct": "((((((.(((((.(((((.....))))).)).((((...(((((.(((....))).))))).))))((((....)))).........((((((........)))))))))..))))))"
    }, 
    {
      "ix": 65, 
      "sprob": 0.00032202232985080887, 
      "struct": "((((((.(((((((((((.....))))).((.((((...(((((.(((....))).))))).)))).))...((((((((....(.......)...))))))))))))))..))))))"
    }, 
    {
      "ix": 18, 
      "sprob": 0.0002737910125029067, 
      "struct": "((((((.(((((((....(((......)))..((((...(((((.(((....))).))))).))))..(((((.((((.........)))).)))))......)))))))..))))))"
    }, 
    {
      "ix": 9, 
      "sprob": 0.0002737910125029067, 
      "struct": "((((((.(((((((((((.((((.........)))).))))...(.(((.(((....))).))).)..(((((.((((.........)))).)))))......)))))))..))))))"
    }, 
    {
      "ix": 73, 
      "sprob": 0.0002737910125029067, 
      "struct": "((((((....((.(((((.....))))).)).((((...(((((.(((....))).))))).))))..(((((.((((.........)))).))))).(((......)))..))))))"
    }, 
    {
      "ix": 31, 
      "sprob": 0.00023278360405036525, 
      "struct": "((((((.(((((((((((.....))))).....(((...(((((.(((....))).)))))....)))(((((.((((.........)))).))))).......))))))..))))))"
    }, 
    {
      "ix": 24, 
      "sprob": 0.00023278360405036525, 
      "struct": "((((((.(((((((((((.....)))))(((.(((((..((.((........))))..))))))))..(((((.((((.........)))).))))).......))))))..))))))"
    }, 
    {
      "ix": 2, 
      "sprob": 0.00023278360405036525, 
      "struct": "((((((...(((.(((((.....))))).)).((((...(((((.(((....))).))))).))))(((((..(((((((................)))))))))))).)..))))))"
    }, 
    {
      "ix": 14, 
      "sprob": 0.00019791813405161437, 
      "struct": "((((((.(((((((.((((((......)))..((((...(((((.(((....))).))))).))))..(((((.((((.........)))).)))))...))))))))))..))))))"
    }, 
    {
      "ix": 43, 
      "sprob": 0.00019791813405161437, 
      "struct": "((((((.(((((.(((((.....))))).)).((((...(((((.(((....))).))))).))))(((((...((((((................))))))))))))))..))))))"
    }, 
    {
      "ix": 26, 
      "sprob": 0.00019791813405161437, 
      "struct": "((((((.(((((((((((.....)))))(((.((((...(((((.(((....))).))))).))))..(((((.((((.........)))).)))))...))).))))))..))))))"
    }, 
    {
      "ix": 53, 
      "sprob": 0.00016827468560886013, 
      "struct": "((((((.(((((((((((.....))))).((.((((...(((((.(((....))).))))).)))).))...((((((((.((.........)).).)))))))))))))..))))))"
    }, 
    {
      "ix": 51, 
      "sprob": 0.00016827468560886013, 
      "struct": "((((((.(((((((((((.....)))))....((((...(((((.(((....))).))))).))))..(((((.(((((......).)))).))))).......))))))..))))))"
    }, 
    {
      "ix": 72, 
      "sprob": 0.0001430711235857566, 
      "struct": "((((((.(((((.(((((.....))))).)).((((...(((((.(((....))).))))).))))..(((((.((((.........)))).))))).((.....)))))..))))))"
    }, 
    {
      "ix": 17, 
      "sprob": 0.0001430711235857566, 
      "struct": "((((((.(((((((...(((......)))((.((((...(((((.(((....))).))))).)))).))....(((((((................))))))))))))))..))))))"
    }, 
    {
      "ix": 47, 
      "sprob": 0.0001430711235857566, 
      "struct": "((((((.(((((.(((((.....))))).)).((((...(((((.(((....))).))))).))))((((((...(((((................))))))))))))))..))))))"
    }, 
    {
      "ix": 33, 
      "sprob": 0.0001430711235857566, 
      "struct": "((((((.(((((((((((.((((.........)))).)))).(.(.(((.(((....))).))).).)(((((.((((.........)))).)))))......)))))))..))))))"
    }, 
    {
      "ix": 10, 
      "sprob": 0.00010342329924529588, 
      "struct": "((((((.((((((((((((((((.........))))...)))))(.(((.(((....))).))).)..(((((.((((.........)))).)))))......)))))))..))))))"
    }, 
    {
      "ix": 5, 
      "sprob": 0.00010342329924529588, 
      "struct": "((((((.(((((((((...........)))).((((...(((((.(((....))).))))).))))..(((((.((((.........)))).)))))........)))))..))))))"
    }, 
    {
      "ix": 11, 
      "sprob": 0.00010342329924529588, 
      "struct": "((((((.((((((((.(((.((((.(((.((.((((...(((((.(((....))).))))).)))).)).))).((((.........)))).))))))).)..)))))))..))))))"
    }, 
    {
      "ix": 59, 
      "sprob": 0.00010342329924529588, 
      "struct": "((((((.(((((((((((.....))))).((.((((...(((((.(((....))).))))).)))).))...((((((((..(..((....)).).))))))))))))))..))))))"
    }, 
    {
      "ix": 68, 
      "sprob": 0.00010342329924529588, 
      "struct": "((((((.(((((((((((.....))))).((.((((...(((((.(((....))).))))).)))).))...((((((((......(...).....))))))))))))))..))))))"
    }, 
    {
      "ix": 48, 
      "sprob": 8.793293878061089e-05, 
      "struct": "((((((.(((((.(((((.....))))).)).((((...(((((.(((....))).))))).))))....((((...))))......((((((........)))))))))..))))))"
    }, 
    {
      "ix": 23, 
      "sprob": 8.793293878061089e-05, 
      "struct": "((((((.(((((((((((.....))))((((.(((((..((.((........))))..))))))))).(((((.((((.........)))).)))))......)))))))..))))))"
    }, 
    {
      "ix": 13, 
      "sprob": 8.793293878061089e-05, 
      "struct": "((((((.(((((((.(.(((......))).).((((...(((((.(((....))).))))).))))..(((((.((((.........)))).)))))......)))))))..))))))"
    }, 
    {
      "ix": 30, 
      "sprob": 6.356499070599898e-05, 
      "struct": "((((((.(((((((((((.....)))))..((((((...(((((.(((....))).))))).)))).....))(((((((................))))))).))))))..))))))"
    }, 
    {
      "ix": 1, 
      "sprob": 6.356499070599898e-05, 
      "struct": "((((((((..((.(((((.....))))).)).((((...(((((.(((....))).))))).))))(((((..(((((((................))))))))))))))..))))))"
    }, 
    {
      "ix": 55, 
      "sprob": 6.356499070599898e-05, 
      "struct": "((((((.(((((((((((.....)))))....((((...(((((.(((....))).))))).))))(((((...))))).((.((((......)))).))....))))))..))))))"
    }, 
    {
      "ix": 25, 
      "sprob": 6.356499070599898e-05, 
      "struct": "((((((.(((((((((((.....)))))((..((((...(((((.(((....))).))))).))))....))((((((((................))))))))))))))..))))))"
    }, 
    {
      "ix": 36, 
      "sprob": 6.356499070599898e-05, 
      "struct": "((((((.(((((((((((.((((.........)))).))))....(((....))).((((...)))).(((((.((((.........)))).)))))......)))))))..))))))"
    }, 
    {
      "ix": 45, 
      "sprob": 6.356499070599898e-05, 
      "struct": "((((((.((((..(((((.....))))).((.((((...(((((.(((....))).))))).)))).)).(.((((((((................)))))))).)))))..))))))"
    }, 
    {
      "ix": 15, 
      "sprob": 6.356499070599898e-05, 
      "struct": "((((((.(((((((..((..((((.(((.((.((((...(((((.(((....))).))))).)))).)).))).((((.........)))).))))..))...)))))))..))))))"
    }, 
    {
      "ix": 57, 
      "sprob": 4.594988066456673e-05, 
      "struct": "((((((.(((((((((((.....))))).((.((((...(((((.(((....))).))))).)))).))...((((((((.(.........)....))))))))))))))..))))))"
    }, 
    {
      "ix": 44, 
      "sprob": 4.594988066456673e-05, 
      "struct": "((((((.(((((.(((((.....))))).((.((((...(((((.(((....))).))))).)))).)).(.((((((((................))))))))))))))..))))))"
    }, 
    {
      "ix": 20, 
      "sprob": 4.594988066456673e-05, 
      "struct": "((((((.(((((((.......(((...)))..((((...(((((.(((....))).))))).))))..(((((.((((.........)))).)))))......)))))))..))))))"
    }, 
    {
      "ix": 63, 
      "sprob": 4.594988066456673e-05, 
      "struct": "((((((.(((((((((((.....))))).((.((((...(((((.(((....))).))))).)))).))...((((((((...((.........))))))))))))))))..))))))"
    }, 
    {
      "ix": 32, 
      "sprob": 3.321626432470588e-05, 
      "struct": "((((((.(((((((((((.....)))))(((.(((((..((.((.(......).))))))))))))..(((((.((((.........)))).))))).......))))))..))))))"
    }, 
    {
      "ix": 28, 
      "sprob": 3.321626432470588e-05, 
      "struct": "((((((.(((((((((((.....))))).((.((((...(((((.(((....))).))))).)))).).)..((((((((................))))))))))))))..))))))"
    }, 
    {
      "ix": 35, 
      "sprob": 3.321626432470588e-05, 
      "struct": "((((((.(((((((((((.....))))).((.((((...((((.((((....))).))))).)))).))...((((((((................))))))))))))))..))))))"
    }, 
    {
      "ix": 50, 
      "sprob": 3.321626432470588e-05, 
      "struct": "((((((.((((((((.(((.((((.(((.((.((((...(((((.(((....))).))))).)))).)).)))....((.(((...))).))))))))).)..)))))))..))))))"
    }, 
    {
      "ix": 34, 
      "sprob": 3.321626432470588e-05, 
      "struct": "((((((.(((((((((((.....))))).((.((((...((((((.((....))).))))).)))).))...((((((((................))))))))))))))..))))))"
    }, 
    {
      "ix": 40, 
      "sprob": 2.8241254714351004e-05, 
      "struct": "((((((.(((((((((((.....)))))....((((...(((((.(((....))).))))).)))).(((.((.((((.........)))).))))).......))))))..))))))"
    }, 
    {
      "ix": 49, 
      "sprob": 2.401138370179774e-05, 
      "struct": "((((((.((.((.(((((.....))))).)).((((...(((((.(((....))).))))).))))(((((.(.((((((................))))))))))))))..))))))"
    }, 
    {
      "ix": 61, 
      "sprob": 2.401138370179774e-05, 
      "struct": "((((((.(((((((((((.....))))).((.((((...(((((.(((....))).))))).)))).))...(((((((...(((.........))))))))))))))))..))))))"
    }, 
    {
      "ix": 4, 
      "sprob": 2.0415047175010314e-05, 
      "struct": "((((((.(((((((((((.....))))).((.((((...(((((.(((....))).))))).)))).))....(((((((................))))))))).))))..))))))"
    }, 
    {
      "ix": 42, 
      "sprob": 2.0415047175010314e-05, 
      "struct": "((((((.((((..(((((.....))))).((.((((...(((((.(((....))).))))).)))).))((.((((((((................))))))))))))))..))))))"
    }, 
    {
      "ix": 69, 
      "sprob": 2.0415047175010314e-05, 
      "struct": "((((((.(((((((((((.....))))).((.((((...(((((.(((....))).))))).)))).))..((((....))))...((((....))))......))))))..))))))"
    }, 
    {
      "ix": 19, 
      "sprob": 1.7357356674396686e-05, 
      "struct": "((((((.(((((((.(((.(............((((...(((((.(((....))).))))).))))..(((((.((((.........)))).))))).).))))))))))..))))))"
    }, 
    {
      "ix": 16, 
      "sprob": 1.7357356674396686e-05, 
      "struct": "((((((.(((((((((.(......)))).((.((((...(((((.(((....))).))))).)))).))...((((((((................))))))))))))))..))))))"
    }, 
    {
      "ix": 56, 
      "sprob": 1.2547291504057152e-05, 
      "struct": "((((((.(((((((((((.....)))))....((((...(((((.(((....))).))))).))))(((((...)))))(((.((((......))))...))).))))))..))))))"
    }, 
    {
      "ix": 29, 
      "sprob": 1.2547291504057152e-05, 
      "struct": "((((((.((((((((.(((.((((.....(((((((...(((((.(((....))).))))).))))(((((...))))).......)))...))))))).)..)))))))..))))))"
    }, 
    {
      "ix": 21, 
      "sprob": 7.711690437849998e-06, 
      "struct": "((((((.(((((((......((.(((...((.((((...(((((.(((....))).))))).)))).))....))).)).((.((((......)))).))...)))))))..))))))"
    }, 
    {
      "ix": 6, 
      "sprob": 7.711690437849998e-06, 
      "struct": "((((((.(((((((..((..((((.(((.((.((((...(((((.(((....))).))))).)))).)).))).((((.........)))).))))..))..))).))))..))))))"
    }, 
    {
      "ix": 22, 
      "sprob": 5.574629232311798e-06, 
      "struct": "((((((.((((((((.(((.(((.((...(((((((...(((((.(((....))).))))).))))(((((...))))).......)))..)))))))).)..)))))))..))))))"
    }
  ], 
  "seq": "UGAAACGGAGGAGACGUUACAGCAACGUGUCAGCUGAAAUGAUGGGCGUAGACGCACGUCAGCGGCGGAAAUGGUUUCUAUCAAAAUGAAAGUGUUUAGAGAUUUUCCUCAAGUUUCA"
}
